buildthedocs-1.0.3.dist-info/WHEEL
buildthedocs-1.0.3.dist-info/entry_points.txt
buildthedocs-1.0.3.dist-info/metadata.json
buildthedocs-1.0.3.dist-info/METADATA
buildthedocs-1.0.3.dist-info/RECORD
buildthedocs-1.0.3.dist-info/DESCRIPTION.rst
buildthedocs-1.0.3.dist-info/top_level.txt
buildthedocs/initializer.py
buildthedocs/utils.py
buildthedocs/__init__.py
buildthedocs/hooks.py
buildthedocs/sources.py
buildthedocs/builder.py
buildthedocs/__main__.py
buildthedocs/resources/extra_conf.py
buildthedocs/resources/sidebar_versions.html
buildthedocs/resources/layout.html
