Metadata-Version: 2.0
Name: buildthedocs
Version: 1.0.3
Summary: A Sphinx documentation building tool on steroids.
Home-page: http://buildthedocs.pietroalbini.io
Author: Pietro Albini
Author-email: pietro@pietroalbini.io
License: MIT
Platform: UNKNOWN
Classifier: Development Status :: 5 - Production/Stable
Classifier: Environment :: Console
Classifier: Framework :: Sphinx
Classifier: Intended Audience :: Developers
Classifier: License :: OSI Approved :: MIT License
Classifier: Natural Language :: English
Classifier: Operating System :: POSIX :: Linux
Classifier: Programming Language :: Python :: 3
Classifier: Programming Language :: Python :: 3.3
Classifier: Programming Language :: Python :: 3.4
Classifier: Programming Language :: Python :: 3 :: Only
Classifier: Topic :: Software Development :: Documentation
Requires-Dist: sphinx
Requires-Dist: jinja2
Requires-Dist: pyyaml
Requires-Dist: click
